{"time":{"updated":"Feb 2, 2025 01:46:17 UTC","updatedISO":"2025-02-02T01:46:17+00:00","updateduk":"Feb 2, 2025 at 01:46 GMT"},"disclaimer":"This data was produced from the CoinDesk Bitcoin Price Index (USD). Non-USD currency data converted using hourly conversion rate from openexchangerates.org","chartName":"Bitcoin","bpi":{"USD":{"code":"USD","symbol":"&#36;","rate":"102,420.93","description":"United States Dollar","rate_float":102420.9295},"GBP":{"code":"GBP","symbol":"&pound;","rate":"82,252.917","description":"British Pound Sterling","rate_float":82252.917},"EUR":{"code":"EUR","symbol":"&euro;","rate":"97,922.295","description":"Euro","rate_float":97922.2951},"CNY":{"code":"CNY","symbol":"&yen;","rate":"744,262.169","description":"Chinese Yuan","rate_float":744262.1687}}}